datasette_sqlite_regex/__init__.py
datasette_sqlite_regex/version.py
datasette_sqlite_regex-0.2.3.dist-info/METADATA
datasette_sqlite_regex-0.2.3.dist-info/WHEEL
datasette_sqlite_regex-0.2.3.dist-info/entry_points.txt
datasette_sqlite_regex-0.2.3.dist-info/top_level.txt
datasette_sqlite_regex-0.2.3.dist-info/RECORD
