Metadata-Version: 2.1
Name: datasette-sqlite-regex
Version: 0.2.3
Home-page: https://github.com/asg017/sqlite-regex
Author: Alex Garcia
License: MIT License, Apache License, Version 2.0
Project-URL: Issues, https://github.com/asg017/sqlite-regex/issues
Project-URL: CI, https://github.com/asg017/sqlite-regex/actions
Project-URL: Changelog, https://github.com/asg017/sqlite-regex/releases
Requires-Python: >=3.7
Requires-Dist: datasette
Requires-Dist: sqlite-regex
Provides-Extra: test
Requires-Dist: pytest ; extra == 'test'
